<?xml version="1.0" encoding="UTF-8"?>

 

<ActueleVertrekTijden>

	<VertrekkendeTrein>
		<RitNummer>2671</RitNummer>
		<VertrekTijd>2017-06-29T19:38:00+0200</VertrekTijd>
		
		
		<EindBestemming>Almere Centrum</EindBestemming>
		<TreinSoort>Intercity</TreinSoort>
		
		
			<Vervoerder>NS</Vervoerder>
		
		<VertrekSpoor wijziging="false">13b</VertrekSpoor>
		
		
	</VertrekkendeTrein>

	<VertrekkendeTrein>
		<RitNummer>3064</RitNummer>
		<VertrekTijd>2017-06-29T19:39:00+0200</VertrekTijd>
		
		
		<EindBestemming>Den Helder</EindBestemming>
		<TreinSoort>Intercity</TreinSoort>
		
			<RouteTekst>A'dam Sloterdijk, Zaandam, Castricum</RouteTekst>
		
		
			<Vervoerder>NS</Vervoerder>
		
		<VertrekSpoor wijziging="false">8</VertrekSpoor>
		
			<ReisTip>Stopt vanaf Alkmaar op tussengelegen stations</ReisTip>
		
		
	</VertrekkendeTrein>

	<VertrekkendeTrein>
		<RitNummer>873</RitNummer>
		<VertrekTijd>2017-06-29T19:40:00+0200</VertrekTijd>
		
		
		<EindBestemming>Maastricht</EindBestemming>
		<TreinSoort>Intercity</TreinSoort>
		
			<RouteTekst>Amstel, Utrecht C, Eindhoven</RouteTekst>
		
		
			<Vervoerder>NS</Vervoerder>
		
		<VertrekSpoor wijziging="false">4</VertrekSpoor>
		
		
	</VertrekkendeTrein>

	<VertrekkendeTrein>
		<RitNummer>15871</RitNummer>
		<VertrekTijd>2017-06-29T19:41:00+0200</VertrekTijd>
		
		
		<EindBestemming>Amersfoort Vathorst</EindBestemming>
		<TreinSoort>Sprinter</TreinSoort>
		
			<RouteTekst>Weesp, Naarden-B, Hilversum</RouteTekst>
		
		
			<Vervoerder>NS</Vervoerder>
		
		<VertrekSpoor wijziging="false">11a</VertrekSpoor>
		
		
	</VertrekkendeTrein>

	<VertrekkendeTrein>
		<RitNummer>4875</RitNummer>
		<VertrekTijd>2017-06-29T19:41:00+0200</VertrekTijd>
		
		
		<EindBestemming>Beverwijk</EindBestemming>
		<TreinSoort>Sprinter</TreinSoort>
		
			<RouteTekst>A'dam Sloterdijk, Haarlem</RouteTekst>
		
		
			<Vervoerder>NS</Vervoerder>
		
		<VertrekSpoor wijziging="false">1</VertrekSpoor>
		
		
	</VertrekkendeTrein>

	<VertrekkendeTrein>
		<RitNummer>4664</RitNummer>
		<VertrekTijd>2017-06-29T19:42:00+0200</VertrekTijd>
		
		
		<EindBestemming>Den Haag Centraal</EindBestemming>
		<TreinSoort>Sprinter</TreinSoort>
		
			<RouteTekst>A'dam Sloterdijk, Schiphol Airport, Leiden C.</RouteTekst>
		
		
			<Vervoerder>NS</Vervoerder>
		
		<VertrekSpoor wijziging="false">13a</VertrekSpoor>
		
		
	</VertrekkendeTrein>

	<VertrekkendeTrein>
		<RitNummer>4064</RitNummer>
		<VertrekTijd>2017-06-29T19:43:00+0200</VertrekTijd>
		
		
		<EindBestemming>Uitgeest</EindBestemming>
		<TreinSoort>Sprinter</TreinSoort>
		
			<RouteTekst>A'dam Sloterdijk, Zaandam</RouteTekst>
		
		
			<Vervoerder>NS</Vervoerder>
		
		<VertrekSpoor wijziging="false">7a</VertrekSpoor>
		
		
	</VertrekkendeTrein>

	<VertrekkendeTrein>
		<RitNummer>9388</RitNummer>
		<VertrekTijd>2017-06-29T19:48:00+0200</VertrekTijd>
		
		
		<EindBestemming>Paris-Nord</EindBestemming>
		<TreinSoort>Thalys</TreinSoort>
		
			<RouteTekst>Rotterdam C., Antwerpen-C., Brussel-Z/Midi</RouteTekst>
		
		
			<Vervoerder>NS International</Vervoerder>
		
		<VertrekSpoor wijziging="false">15b</VertrekSpoor>
		
		
	</VertrekkendeTrein>

	<VertrekkendeTrein>
		<RitNummer>2179</RitNummer>
		<VertrekTijd>2017-06-29T19:49:00+0200</VertrekTijd>
		
		
		<EindBestemming>Den Haag Centraal</EindBestemming>
		<TreinSoort>Intercity</TreinSoort>
		
			<RouteTekst>A'dam Sloterdijk, Haarlem, Leiden C.</RouteTekst>
		
		
			<Vervoerder>NS</Vervoerder>
		
		<VertrekSpoor wijziging="true">2a</VertrekSpoor>
		
		
	</VertrekkendeTrein>

	<VertrekkendeTrein>
		<RitNummer>4075</RitNummer>
		<VertrekTijd>2017-06-29T19:49:00+0200</VertrekTijd>
		
		
		<EindBestemming>Rotterdam Centraal</EindBestemming>
		<TreinSoort>Sprinter</TreinSoort>
		
			<RouteTekst>Duivendrecht, Breukelen, Woerden</RouteTekst>
		
		
			<Vervoerder>NS</Vervoerder>
		
		<VertrekSpoor wijziging="true">4b</VertrekSpoor>
		
		
	</VertrekkendeTrein>

	<VertrekkendeTrein>
		<RitNummer>1066</RitNummer>
		<VertrekTijd>2017-06-29T19:51:00+0200</VertrekTijd>
		
		
		<EindBestemming>Rotterdam Centraal</EindBestemming>
		<TreinSoort>Intercity direct</TreinSoort>
		
			<RouteTekst>Schiphol Airport</RouteTekst>
		
		
			<Vervoerder>NS</Vervoerder>
		
		<VertrekSpoor wijziging="false">14a</VertrekSpoor>
		
		
	</VertrekkendeTrein>

	<VertrekkendeTrein>
		<RitNummer>14673</RitNummer>
		<VertrekTijd>2017-06-29T19:53:00+0200</VertrekTijd>
		
		
		<EindBestemming>Zwolle</EindBestemming>
		<TreinSoort>Sprinter</TreinSoort>
		
			<RouteTekst>Weesp, Almere C., Lelystad C.</RouteTekst>
		
		
			<Vervoerder>NS</Vervoerder>
		
		<VertrekSpoor wijziging="false">10b</VertrekSpoor>
		
		
	</VertrekkendeTrein>

	<VertrekkendeTrein>
		<RitNummer>9268</RitNummer>
		<VertrekTijd>2017-06-29T19:54:00+0200</VertrekTijd>
		
		
		<EindBestemming>Brussel-Zuid/Midi</EindBestemming>
		<TreinSoort>Intercity</TreinSoort>
		
			<RouteTekst>Schiphol Airport, Rotterdam C., Antwerpen-C.</RouteTekst>
		
		
			<Vervoerder>NS International</Vervoerder>
		
		<VertrekSpoor wijziging="false">14b</VertrekSpoor>
		
		
	</VertrekkendeTrein>

	<VertrekkendeTrein>
		<RitNummer>3073</RitNummer>
		<VertrekTijd>2017-06-29T19:55:00+0200</VertrekTijd>
		
		
		<EindBestemming>Nijmegen</EindBestemming>
		<TreinSoort>Intercity</TreinSoort>
		
			<RouteTekst>Amstel, Utrecht C, De Klomp</RouteTekst>
		
		
			<Vervoerder>NS</Vervoerder>
		
		<VertrekSpoor wijziging="false">4a</VertrekSpoor>
		
		
	</VertrekkendeTrein>

	<VertrekkendeTrein>
		<RitNummer>5481</RitNummer>
		<VertrekTijd>2017-06-29T19:56:00+0200</VertrekTijd>
		
		
		<EindBestemming>Zandvoort aan Zee</EindBestemming>
		<TreinSoort>Sprinter</TreinSoort>
		
			<RouteTekst>A'dam Sloterdijk, Haarlem</RouteTekst>
		
		
			<Vervoerder>NS</Vervoerder>
		
		<VertrekSpoor wijziging="false">1</VertrekSpoor>
		
		
	</VertrekkendeTrein>

	<VertrekkendeTrein>
		<RitNummer>1573</RitNummer>
		<VertrekTijd>2017-06-29T20:00:00+0200</VertrekTijd>
		
		
		<EindBestemming>Amersfoort</EindBestemming>
		<TreinSoort>Intercity</TreinSoort>
		
			<RouteTekst>Hilversum</RouteTekst>
		
		
			<Vervoerder>NS</Vervoerder>
		
		<VertrekSpoor wijziging="false">11b</VertrekSpoor>
		
		
	</VertrekkendeTrein>

	<VertrekkendeTrein>
		<RitNummer>5866</RitNummer>
		<VertrekTijd>2017-06-29T20:01:00+0200</VertrekTijd>
		
		
		<EindBestemming>Hoofddorp</EindBestemming>
		<TreinSoort>Sprinter</TreinSoort>
		
			<RouteTekst>A'dam Sloterdijk, Schiphol Airport</RouteTekst>
		
		
			<Vervoerder>NS</Vervoerder>
		
		<VertrekSpoor wijziging="false">11a</VertrekSpoor>
		
		
	</VertrekkendeTrein>

	<VertrekkendeTrein>
		<RitNummer>2268</RitNummer>
		<VertrekTijd>2017-06-29T20:04:00+0200</VertrekTijd>
		
		
		<EindBestemming>Vlissingen</EindBestemming>
		<TreinSoort>Intercity</TreinSoort>
		
			<RouteTekst>A'dam Sloterdijk, Haarlem, Rotterdam C.</RouteTekst>
		
		
			<Vervoerder>NS</Vervoerder>
		
		<VertrekSpoor wijziging="false">2a</VertrekSpoor>
		
		
	</VertrekkendeTrein>

	<VertrekkendeTrein>
		<RitNummer>4568</RitNummer>
		<VertrekTijd>2017-06-29T20:06:00+0200</VertrekTijd>
		
		
		<EindBestemming>Enkhuizen</EindBestemming>
		<TreinSoort>Intercity</TreinSoort>
		
			<RouteTekst>A'dam Sloterdijk, Hoorn</RouteTekst>
		
		
			<Vervoerder>NS</Vervoerder>
		
		<VertrekSpoor wijziging="false">7a</VertrekSpoor>
		
		
	</VertrekkendeTrein>

	<VertrekkendeTrein>
		<RitNummer>966</RitNummer>
		<VertrekTijd>2017-06-29T20:07:00+0200</VertrekTijd>
		
		
		<EindBestemming>Breda</EindBestemming>
		<TreinSoort>Intercity direct</TreinSoort>
		
			<RouteTekst>Schiphol Airport, Rotterdam C.</RouteTekst>
		
		
			<Vervoerder>NS</Vervoerder>
		
		<VertrekSpoor wijziging="false">15a</VertrekSpoor>
		
		
	</VertrekkendeTrein>

	<VertrekkendeTrein>
		<RitNummer>2673</RitNummer>
		<VertrekTijd>2017-06-29T20:08:00+0200</VertrekTijd>
		
		
		<EindBestemming>Almere Centrum</EindBestemming>
		<TreinSoort>Intercity</TreinSoort>
		
		
			<Vervoerder>NS</Vervoerder>
		
		<VertrekSpoor wijziging="false">13b</VertrekSpoor>
		
		
	</VertrekkendeTrein>

	<VertrekkendeTrein>
		<RitNummer>3066</RitNummer>
		<VertrekTijd>2017-06-29T20:09:00+0200</VertrekTijd>
		
		
		<EindBestemming>Den Helder</EindBestemming>
		<TreinSoort>Intercity</TreinSoort>
		
			<RouteTekst>A'dam Sloterdijk, Zaandam, Castricum</RouteTekst>
		
		
			<Vervoerder>NS</Vervoerder>
		
		<VertrekSpoor wijziging="false">8a</VertrekSpoor>
		
			<ReisTip>Stopt vanaf Alkmaar op tussengelegen stations</ReisTip>
		
		
	</VertrekkendeTrein>

	<VertrekkendeTrein>
		<RitNummer>875</RitNummer>
		<VertrekTijd>2017-06-29T20:10:00+0200</VertrekTijd>
		
		
		<EindBestemming>Maastricht</EindBestemming>
		<TreinSoort>Intercity</TreinSoort>
		
			<RouteTekst>Amstel, Utrecht C, Eindhoven</RouteTekst>
		
		
			<Vervoerder>NS</Vervoerder>
		
		<VertrekSpoor wijziging="true">5b</VertrekSpoor>
		
		
	</VertrekkendeTrein>

	<VertrekkendeTrein>
		<RitNummer>15873</RitNummer>
		<VertrekTijd>2017-06-29T20:11:00+0200</VertrekTijd>
		
		
		<EindBestemming>Amersfoort Vathorst</EindBestemming>
		<TreinSoort>Sprinter</TreinSoort>
		
			<RouteTekst>Weesp, Naarden-B, Hilversum</RouteTekst>
		
		
			<Vervoerder>NS</Vervoerder>
		
		<VertrekSpoor wijziging="false">10a</VertrekSpoor>
		
		
	</VertrekkendeTrein>

	<VertrekkendeTrein>
		<RitNummer>4877</RitNummer>
		<VertrekTijd>2017-06-29T20:11:00+0200</VertrekTijd>
		
		
		<EindBestemming>Beverwijk</EindBestemming>
		<TreinSoort>Sprinter</TreinSoort>
		
			<RouteTekst>A'dam Sloterdijk, Haarlem</RouteTekst>
		
		
			<Vervoerder>NS</Vervoerder>
		
		<VertrekSpoor wijziging="false">1</VertrekSpoor>
		
		
	</VertrekkendeTrein>

	<VertrekkendeTrein>
		<RitNummer>4666</RitNummer>
		<VertrekTijd>2017-06-29T20:11:00+0200</VertrekTijd>
		
		
		<EindBestemming>Den Haag Centraal</EindBestemming>
		<TreinSoort>Sprinter</TreinSoort>
		
			<RouteTekst>A'dam Sloterdijk, Schiphol Airport, Leiden C.</RouteTekst>
		
		
			<Vervoerder>NS</Vervoerder>
		
		<VertrekSpoor wijziging="false">13a</VertrekSpoor>
		
		
	</VertrekkendeTrein>

	<VertrekkendeTrein>
		<RitNummer>4066</RitNummer>
		<VertrekTijd>2017-06-29T20:13:00+0200</VertrekTijd>
		
		
		<EindBestemming>Uitgeest</EindBestemming>
		<TreinSoort>Sprinter</TreinSoort>
		
			<RouteTekst>A'dam Sloterdijk, Zaandam</RouteTekst>
		
		
			<Vervoerder>NS</Vervoerder>
		
		<VertrekSpoor wijziging="false">7a</VertrekSpoor>
		
		
	</VertrekkendeTrein>

	<VertrekkendeTrein>
		<RitNummer>9394</RitNummer>
		<VertrekTijd>2017-06-29T20:17:00+0200</VertrekTijd>
		
		
		<EindBestemming>Brussel-Zuid/Midi</EindBestemming>
		<TreinSoort>Thalys</TreinSoort>
		
			<RouteTekst>Rotterdam C., Antwerpen-C.</RouteTekst>
		
		
			<Vervoerder>NS International</Vervoerder>
		
		<VertrekSpoor wijziging="false">15b</VertrekSpoor>
		
		
	</VertrekkendeTrein>

	<VertrekkendeTrein>
		<RitNummer>2181</RitNummer>
		<VertrekTijd>2017-06-29T20:19:00+0200</VertrekTijd>
		
		
		<EindBestemming>Den Haag Centraal</EindBestemming>
		<TreinSoort>Intercity</TreinSoort>
		
			<RouteTekst>A'dam Sloterdijk, Haarlem, Leiden C.</RouteTekst>
		
		
			<Vervoerder>NS</Vervoerder>
		
		<VertrekSpoor wijziging="false">2a</VertrekSpoor>
		
		
	</VertrekkendeTrein>

	<VertrekkendeTrein>
		<RitNummer>4077</RitNummer>
		<VertrekTijd>2017-06-29T20:19:00+0200</VertrekTijd>
		
		
		<EindBestemming>Rotterdam Centraal</EindBestemming>
		<TreinSoort>Sprinter</TreinSoort>
		
			<RouteTekst>Duivendrecht, Breukelen, Woerden</RouteTekst>
		
		
			<Vervoerder>NS</Vervoerder>
		
		<VertrekSpoor wijziging="true">4b</VertrekSpoor>
		
		
	</VertrekkendeTrein>

	<VertrekkendeTrein>
		<RitNummer>1068</RitNummer>
		<VertrekTijd>2017-06-29T20:22:00+0200</VertrekTijd>
		
		
		<EindBestemming>Rotterdam Centraal</EindBestemming>
		<TreinSoort>Intercity direct</TreinSoort>
		
			<RouteTekst>Schiphol Airport</RouteTekst>
		
		
			<Vervoerder>NS</Vervoerder>
		
		<VertrekSpoor wijziging="false">14b</VertrekSpoor>
		
		
			<Opmerkingen>
				
					
						<Opmerking>
							Rijdt vandaag niet
						</Opmerking>
					
				
			</Opmerkingen>
		
	</VertrekkendeTrein>

	<VertrekkendeTrein>
		<RitNummer>14675</RitNummer>
		<VertrekTijd>2017-06-29T20:23:00+0200</VertrekTijd>
		
		
		<EindBestemming>Zwolle</EindBestemming>
		<TreinSoort>Sprinter</TreinSoort>
		
			<RouteTekst>Weesp, Almere C., Lelystad C.</RouteTekst>
		
		
			<Vervoerder>NS</Vervoerder>
		
		<VertrekSpoor wijziging="false">10b</VertrekSpoor>
		
		
	</VertrekkendeTrein>

	<VertrekkendeTrein>
		<RitNummer>3075</RitNummer>
		<VertrekTijd>2017-06-29T20:25:00+0200</VertrekTijd>
		
		
		<EindBestemming>Nijmegen</EindBestemming>
		<TreinSoort>Intercity</TreinSoort>
		
			<RouteTekst>Amstel, Utrecht C, De Klomp</RouteTekst>
		
		
			<Vervoerder>NS</Vervoerder>
		
		<VertrekSpoor wijziging="false">4a</VertrekSpoor>
		
		
	</VertrekkendeTrein>

	<VertrekkendeTrein>
		<RitNummer>5483</RitNummer>
		<VertrekTijd>2017-06-29T20:26:00+0200</VertrekTijd>
		
		
		<EindBestemming>Zandvoort aan Zee</EindBestemming>
		<TreinSoort>Sprinter</TreinSoort>
		
			<RouteTekst>A'dam Sloterdijk, Haarlem</RouteTekst>
		
		
			<Vervoerder>NS</Vervoerder>
		
		<VertrekSpoor wijziging="false">1</VertrekSpoor>
		
		
	</VertrekkendeTrein>

	<VertrekkendeTrein>
		<RitNummer>1575</RitNummer>
		<VertrekTijd>2017-06-29T20:30:00+0200</VertrekTijd>
		
		
		<EindBestemming>Amersfoort</EindBestemming>
		<TreinSoort>Intercity</TreinSoort>
		
			<RouteTekst>Hilversum</RouteTekst>
		
		
			<Vervoerder>NS</Vervoerder>
		
		<VertrekSpoor wijziging="false">11b</VertrekSpoor>
		
		
	</VertrekkendeTrein>

	<VertrekkendeTrein>
		<RitNummer>5868</RitNummer>
		<VertrekTijd>2017-06-29T20:32:00+0200</VertrekTijd>
		
		
		<EindBestemming>Hoofddorp</EindBestemming>
		<TreinSoort>Sprinter</TreinSoort>
		
			<RouteTekst>A'dam Sloterdijk, Schiphol Airport</RouteTekst>
		
		
			<Vervoerder>NS</Vervoerder>
		
		<VertrekSpoor wijziging="false">13a</VertrekSpoor>
		
		
	</VertrekkendeTrein>

	<VertrekkendeTrein>
		<RitNummer>2270</RitNummer>
		<VertrekTijd>2017-06-29T20:34:00+0200</VertrekTijd>
		
		
		<EindBestemming>Vlissingen</EindBestemming>
		<TreinSoort>Intercity</TreinSoort>
		
			<RouteTekst>A'dam Sloterdijk, Haarlem, Rotterdam C.</RouteTekst>
		
		
			<Vervoerder>NS</Vervoerder>
		
		<VertrekSpoor wijziging="false">2a</VertrekSpoor>
		
		
	</VertrekkendeTrein>

	<VertrekkendeTrein>
		<RitNummer>4570</RitNummer>
		<VertrekTijd>2017-06-29T20:36:00+0200</VertrekTijd>
		
		
		<EindBestemming>Enkhuizen</EindBestemming>
		<TreinSoort>Intercity</TreinSoort>
		
			<RouteTekst>A'dam Sloterdijk, Hoorn</RouteTekst>
		
		
			<Vervoerder>NS</Vervoerder>
		
		<VertrekSpoor wijziging="false">10a</VertrekSpoor>
		
		
	</VertrekkendeTrein>

	<VertrekkendeTrein>
		<RitNummer>968</RitNummer>
		<VertrekTijd>2017-06-29T20:37:00+0200</VertrekTijd>
		
		
		<EindBestemming>Breda</EindBestemming>
		<TreinSoort>Intercity direct</TreinSoort>
		
			<RouteTekst>Schiphol Airport, Rotterdam C.</RouteTekst>
		
		
			<Vervoerder>NS</Vervoerder>
		
		<VertrekSpoor wijziging="false">15a</VertrekSpoor>
		
		
	</VertrekkendeTrein>

	<VertrekkendeTrein>
		<RitNummer>2675</RitNummer>
		<VertrekTijd>2017-06-29T20:38:00+0200</VertrekTijd>
		
		
		<EindBestemming>Almere Centrum</EindBestemming>
		<TreinSoort>Intercity</TreinSoort>
		
		
			<Vervoerder>NS</Vervoerder>
		
		<VertrekSpoor wijziging="false">13b</VertrekSpoor>
		
		
	</VertrekkendeTrein>

</ActueleVertrekTijden>